MANIFEST.in
account_pcg_morocco.xml
account_type.xml
l10n_ma_journal.xml
l10n_ma_tax.xml
l10n_ma_wizard.xml
setup.py
./__init__.py
./__openerp__.py
./l10n_ma.py
i18n/ar.po
i18n/ca.po
i18n/da.po
i18n/de.po
i18n/es.po
i18n/es_CR.po
i18n/es_MX.po
i18n/es_PY.po
i18n/es_VE.po
i18n/fr.po
i18n/gl.po
i18n/hu.po
i18n/it.po
i18n/l10n_ma.pot
i18n/nl.po
i18n/pt.po
i18n/pt_BR.po
i18n/sl.po
i18n/sr@latin.po
i18n/tr.po
images/config_chart_l10n_ma.jpeg
images/l10n_ma_chart.jpeg
openerp_l10n_ma.egg-info/PKG-INFO
openerp_l10n_ma.egg-info/SOURCES.txt
openerp_l10n_ma.egg-info/dependency_links.txt
openerp_l10n_ma.egg-info/requires.txt
openerp_l10n_ma.egg-info/top_level.txt
security/ir.model.access.csv
static/src/img/icon.png